{
  "id": "bacopa-monnieri",
  "commonName": "Herb-of-grace",
  "scientificName": "Bacopa monnieri",
  "description": "A native plant species. This plant adds natural beauty to native gardens.",
  "requirements": {
    "sun": "full-sun",
    "moisture": "medium",
    "soil": "loam"
  },
  "characteristics": {
    "height": 24,
    "width": 18,
    "bloomColor": [
      "white"
    ],
    "bloomTime": [
      "summer"
    ],
    "perennial": true,
    "nativeRange": [
      "United States"
    ],
    "hardinessZones": [
      "5",
      "6",
      "7",
      "8"
    ]
  },
  "relationships": {
    "hostPlantTo": [],
    "foodFor": [
      "butterflies",
      "bees",
      "native bees"
    ],
    "usefulFor": [
      "pollinator garden",
      "native garden"
    ],
    "shelterFor": [
      "ground-nesting birds"
    ]
  },
  "imageUrl": "/images/plants/bacopa-monnieri/bacopa-monnieri-2025-10-23T01-26-31-974Z.jpg",
  "thumbnailUrl": "/images/plants/bacopa-monnieri/bacopa-monnieri-2025-10-23T01-26-31-974Z-thumb.jpg",
  "usdaPlantId": "BAMO",
  "distribution": {
    "fipsCodes": [
      "01003",
      "01097",
      "06025",
      "06065",
      "06073",
      "12005",
      "12007",
      "12009",
      "12011",
      "12015",
      "12017",
      "12019",
      "12021",
      "12029",
      "12031",
      "12033",
      "12035",
      "12037",
      "12043",
      "12045",
      "12051",
      "12053",
      "12055",
      "12057",
      "12061",
      "12069",
      "12071",
      "12075",
      "12077",
      "12081",
      "12083",
      "12085",
      "12086",
      "12087",
      "12089",
      "12091",
      "12093",
      "12095",
      "12097",
      "12099",
      "12101",
      "12103",
      "12105",
      "12107",
      "12109",
      "12111",
      "12113",
      "12115",
      "12117",
      "12123",
      "12127",
      "12129",
      "12131",
      "13003",
      "13039",
      "13051",
      "13127",
      "13179",
      "13185",
      "13191",
      "15001",
      "15003",
      "15007",
      "15009",
      "22003",
      "22011",
      "22019",
      "22023",
      "22039",
      "22043",
      "22045",
      "22047",
      "22049",
      "22051",
      "22057",
      "22059",
      "22063",
      "22067",
      "22069",
      "22071",
      "22073",
      "22075",
      "22077",
      "22079",
      "22083",
      "22085",
      "22087",
      "22089",
      "22093",
      "22095",
      "22097",
      "22101",
      "22103",
      "22105",
      "22107",
      "22109",
      "22113",
      "22127",
      "28045",
      "28047",
      "28059",
      "28151",
      "28157",
      "37013",
      "37019",
      "37031",
      "37049",
      "37055",
      "37095",
      "37129",
      "37137",
      "37141",
      "45013",
      "45019",
      "45043",
      "45051",
      "48007",
      "48021",
      "48027",
      "48029",
      "48041",
      "48043",
      "48053",
      "48057",
      "48061",
      "48091",
      "48105",
      "48121",
      "48137",
      "48167",
      "48171",
      "48175",
      "48177",
      "48201",
      "48209",
      "48215",
      "48245",
      "48255",
      "48261",
      "48273",
      "48279",
      "48299",
      "48309",
      "48355",
      "48361",
      "48371",
      "48385",
      "48409",
      "48427",
      "48443",
      "48453",
      "48455",
      "48463",
      "48465",
      "48477",
      "48479",
      "48489",
      "48491",
      "48493",
      "51001",
      "51131",
      "51810",
      "74300"
    ],
    "statesFips": [
      "01",
      "04",
      "06",
      "12",
      "13",
      "15",
      "22",
      "24",
      "28",
      "37",
      "40",
      "45",
      "48",
      "51",
      "66",
      "72",
      "74",
      "78"
    ]
  }
}
