{
  "id": "penstemon-cobaea",
  "commonName": "Prairie Penstemon",
  "scientificName": "Penstemon cobaea",
  "description": "A native plant species. This plant adds natural beauty to native gardens.",
  "requirements": {
    "sun": "full-sun",
    "moisture": "medium",
    "soil": "loam"
  },
  "characteristics": {
    "height": 24,
    "width": 18,
    "bloomColor": [
      "white"
    ],
    "bloomTime": [
      "spring"
    ],
    "perennial": true,
    "nativeRange": [
      "United States"
    ],
    "hardinessZones": [
      "3",
      "4",
      "5",
      "6",
      "7",
      "8"
    ]
  },
  "relationships": {
    "hostPlantTo": [],
    "foodFor": [
      "butterflies",
      "bees"
    ],
    "usefulFor": [
      "pollinator garden",
      "native garden"
    ],
    "shelterFor": [
      "ground-nesting birds"
    ]
  },
  "imageUrl": "/images/plants/penstemon-cobaea/penstemon-cobaea-2025-10-23T01-26-03-409Z.jpg",
  "thumbnailUrl": "/images/plants/penstemon-cobaea/penstemon-cobaea-2025-10-23T01-26-03-409Z-thumb.jpg",
  "usdaPlantId": "PECO4",
  "distribution": {
    "fipsCodes": [
      "04005",
      "05005",
      "05009",
      "05015",
      "05049",
      "05057",
      "05065",
      "05081",
      "05089",
      "05129",
      "05133",
      "05135",
      "05137",
      "08071",
      "17089",
      "20001",
      "20003",
      "20007",
      "20009",
      "20011",
      "20013",
      "20015",
      "20017",
      "20019",
      "20027",
      "20029",
      "20031",
      "20035",
      "20041",
      "20045",
      "20047",
      "20049",
      "20051",
      "20053",
      "20055",
      "20059",
      "20061",
      "20073",
      "20077",
      "20079",
      "20085",
      "20087",
      "20089",
      "20091",
      "20095",
      "20097",
      "20099",
      "20105",
      "20107",
      "20111",
      "20113",
      "20115",
      "20117",
      "20121",
      "20123",
      "20125",
      "20127",
      "20131",
      "20133",
      "20139",
      "20141",
      "20143",
      "20149",
      "20155",
      "20157",
      "20159",
      "20161",
      "20163",
      "20165",
      "20167",
      "20169",
      "20173",
      "20177",
      "20183",
      "20191",
      "20197",
      "20201",
      "20205",
      "20207",
      "29009",
      "29013",
      "29043",
      "29153",
      "29209",
      "29213",
      "31095",
      "31109",
      "31131",
      "31147",
      "31181",
      "35037",
      "35049",
      "35055",
      "39085",
      "40011",
      "40013",
      "40015",
      "40019",
      "40023",
      "40027",
      "40031",
      "40043",
      "40049",
      "40051",
      "40055",
      "40069",
      "40075",
      "40083",
      "40085",
      "40087",
      "40089",
      "40093",
      "40095",
      "40099",
      "40109",
      "40113",
      "40117",
      "40123",
      "40125",
      "40127",
      "40129",
      "40133",
      "40137",
      "40141",
      "40143",
      "40151",
      "48001",
      "48009",
      "48027",
      "48029",
      "48031",
      "48041",
      "48049",
      "48051",
      "48059",
      "48075",
      "48077",
      "48083",
      "48085",
      "48087",
      "48097",
      "48099",
      "48113",
      "48119",
      "48121",
      "48133",
      "48139",
      "48143",
      "48147",
      "48149",
      "48155",
      "48175",
      "48177",
      "48181",
      "48185",
      "48193",
      "48209",
      "48231",
      "48239",
      "48255",
      "48265",
      "48279",
      "48281",
      "48285",
      "48303",
      "48309",
      "48315",
      "48327",
      "48339",
      "48353",
      "48363",
      "48367",
      "48383",
      "48395",
      "48411",
      "48417",
      "48429",
      "48439",
      "48441",
      "48443",
      "48453",
      "48463",
      "48469",
      "48477",
      "48485",
      "48487",
      "48491",
      "48497",
      "48503"
    ],
    "statesFips": [
      "04",
      "05",
      "08",
      "17",
      "19",
      "20",
      "29",
      "31",
      "35",
      "39",
      "40",
      "48"
    ]
  }
}
