{
  "id": "taenidia-integerrima",
  "commonName": "Yellow Pimpernel",
  "scientificName": "Taenidia integerrima",
  "description": "Delicate native wildflower in the carrot family with yellow umbel flowers. Host plant for Black Swallowtail butterfly. Prefers dry, rocky or sandy soils. Important early spring nectar source.",
  "requirements": {
    "sun": "full-sun",
    "moisture": "dry",
    "soil": "sand"
  },
  "characteristics": {
    "height": 30,
    "width": 18,
    "bloomColor": [
      "yellow"
    ],
    "bloomTime": [
      "spring",
      "early summer"
    ],
    "perennial": true,
    "nativeRange": [
      "New York",
      "New Jersey",
      "Pennsylvania",
      "Delaware",
      "Maryland",
      "Virginia",
      "West Virginia",
      "North Carolina",
      "South Carolina",
      "Georgia",
      "Alabama",
      "Tennessee",
      "Kentucky",
      "Ohio",
      "Indiana",
      "Illinois",
      "Michigan",
      "Wisconsin",
      "Minnesota",
      "Iowa",
      "Missouri",
      "Arkansas",
      "Oklahoma",
      "Texas"
    ],
    "hardinessZones": [
      "4",
      "5",
      "6",
      "7",
      "8"
    ]
  },
  "relationships": {
    "hostPlantTo": [
      "Papilio polyxenes asterius"
    ],
    "foodFor": [
      "butterflies",
      "bees",
      "native bees"
    ],
    "shelterFor": [
      "ground-nesting birds"
    ],
    "usefulFor": [
      "pollinator garden",
      "dry garden",
      "prairie restoration"
    ]
  },
  "imageUrl": "/images/plants/taenidia-integerrima/taenidia-integerrima-2025-10-23T19-46-43-085Z.jpg",
  "thumbnailUrl": "/images/plants/taenidia-integerrima/taenidia-integerrima-2025-10-23T19-46-43-085Z-thumb.jpg"
}